<T3DataStructure>
	<meta>
		<langDisable>1</langDisable>
	</meta>
	<sheets>
		<sDEF>
			<ROOT>
				<TCEforms>
					<sheetTitle>LLL:EXT:jk_poll/locallang_db.xml:tt_content.pi_flexform.sheet_settings</sheetTitle>
				</TCEforms>
				<type>array</type>
				<el>
					<what_to_display>
						<TCEforms>
							<label>LLL:EXT:jk_poll/locallang_db.xml:tt_content.pi_flexform.what_to_display</label>
							<config>
								<type>select</type>
								<items type="array">
								<numIndex index="0" type="array">
									<numIndex index="0">POLL</numIndex>
									<numIndex index="1">POLL</numIndex>
								</numIndex>
								<numIndex index="1" type="array">
									<numIndex index="0">LIST</numIndex>
									<numIndex index="1">LIST</numIndex>
								</numIndex>
								<numIndex index="2" type="array">
									<numIndex index="0">RESULT</numIndex>
									<numIndex index="1">RESULT</numIndex>
								</numIndex>
								</items>
								<maxitems>2</maxitems>
								<size>5</size>
								<multiple>1</multiple>
								<selectedListStyle>width:150px</selectedListStyle>
								<itemListStyle>width:150px</itemListStyle>
							</config>
						</TCEforms>
					</what_to_display>
					
					<templatefile>
						<TCEforms>
							<label>LLL:EXT:jk_poll/locallang_db.xml:tt_content.pi_flexform.templatefile</label>
							<config>
								<type>input</type>
								<size>25</size>
							</config>
						</TCEforms>
					</templatefile>
					<css_file>
						<TCEforms>
							<label>LLL:EXT:jk_poll/locallang_db.xml:tt_content.pi_flexform.css_file</label>
							<config>
								<type>input</type>
								<size>25</size>
							</config>
						</TCEforms>
					</css_file>
					<vote_language_specific>
						<TCEforms>
							<label>LLL:EXT:jk_poll/locallang_db.xml:tx_jkpoll_poll.vote_language_specific</label>
							<config>
								<type>check</type>
							</config>
						</TCEforms>
					</vote_language_specific>
					<check_language_specific>
						<TCEforms>
							<label>LLL:EXT:jk_poll/locallang_db.xml:tx_jkpoll_poll.check_language_specific</label>
							<config>
								<type>check</type>
							</config>
						</TCEforms>
					</check_language_specific>  
				</el>
			</ROOT>
		</sDEF>
	
		<s_poll>
			<ROOT>
				<TCEforms>
					<sheetTitle>LLL:EXT:jk_poll/locallang_db.xml:tt_content.pi_flexform.sheet_poll</sheetTitle>
				</TCEforms>
				<type>array</type>
				<el>	     
					<first_answer_selected>
						<TCEforms>
							<label>LLL:EXT:jk_poll/locallang_db.xml:tx_jkpoll_poll.first_answer_selected</label>
							<config>
								<type>check</type>
							</config>
						</TCEforms>
					</first_answer_selected>
					<checkbox>
						<TCEforms>
							<label>LLL:EXT:jk_poll/locallang_db.xml:tt_content.pi_flexform.checkbox</label>
							<config>
								<type>check</type>
							</config>
						</TCEforms>
					</checkbox>
					<cookie>
						<TCEforms>
							<label>LLL:EXT:jk_poll/locallang_db.xml:tt_content.pi_flexform.cookie</label>
							<config>
								<type>input</type>
								<size>5</size>
							</config>
						</TCEforms>
					</cookie>
					<fe_user>
						<TCEforms>
							<label>LLL:EXT:jk_poll/locallang_db.xml:tt_content.pi_flexform.fe_user</label>
							<config>
								<type>check</type>
							</config>
						</TCEforms>
					</fe_user>
					<check_ip>
						<TCEforms>
							<label>LLL:EXT:jk_poll/locallang_db.xml:tt_content.pi_flexform.check_ip</label>
							<config>
								<type>check</type>
							</config>
						</TCEforms>
					</check_ip>
					<time>
						<TCEforms>
							<label>LLL:EXT:jk_poll/locallang_db.xml:tt_content.pi_flexform.time</label>
							<config>
								<type>input</type>
								<size>5</size>
							</config>
						</TCEforms>
					</time>
					<captcha>
						<TCEforms>
							<label>LLL:EXT:jk_poll/locallang_db.xml:tt_content.pi_flexform.captcha</label>
							<config>
								<type>select</type>
								<items type="array">
								<numIndex index="0" type="array">
									<numIndex index="0"></numIndex>
									<numIndex index="1"></numIndex>
								</numIndex>
								<numIndex index="1" type="array">
									<numIndex index="0">captcha</numIndex>
									<numIndex index="1">captcha</numIndex>
								</numIndex>
								<numIndex index="2" type="array">
									<numIndex index="0">sr_freecap</numIndex>
									<numIndex index="1">sr_freecap</numIndex>
								</numIndex>
								</items>
								<maxitems>1</maxitems>
								<size>1</size>
								<multiple>0</multiple>
								<selectedListStyle>width:150px</selectedListStyle>
								<itemListStyle>width:150px</itemListStyle>
							</config>
						</TCEforms>
					</captcha>
					<comments>
						<TCEforms>
							<label>LLL:EXT:jk_poll/locallang_db.xml:tt_content.pi_flexform.comments</label>
							<config>
								<type>check</type>
							</config>
						</TCEforms>
					</comments>
					<PIDforward>
						<TCEforms>
							<exclude>1</exclude>
							<label>LLL:EXT:jk_poll/locallang_db.xml:tt_content.pi_flexform.PIDforward</label>
							<config>
								<type>group</type>
								<internal_type>db</internal_type>
								<allowed>pages</allowed>
								<size>1</size>
								<maxitems>1</maxitems>
								<minitems>0</minitems>
								<show_thumbs>1</show_thumbs>
							</config>
						</TCEforms>
					</PIDforward>
					<list>
						<TCEforms>
							<label>LLL:EXT:jk_poll/locallang_db.xml:tt_content.pi_flexform.list</label>
							<config>
								<type>check</type>
							</config>
						</TCEforms>
					</list>
					<link_to_result>
						<TCEforms>
							<label>LLL:EXT:jk_poll/locallang_db.xml:tt_content.pi_flexform.link_to_result</label>
							<config>
								<type>check</type>
							</config>
						</TCEforms>
					</link_to_result>
				</el>
			</ROOT>
		</s_poll>
	
		<s_result>
			<ROOT>
				<TCEforms>
					<sheetTitle>LLL:EXT:jk_poll/locallang_db.xml:tt_content.pi_flexform.sheet_result</sheetTitle>
				</TCEforms>
				<type>array</type>
				<el>	     
					<type>
						<TCEforms>
							<label>LLL:EXT:jk_poll/locallang_db.xml:tt_content.pi_flexform.type</label>
							<config>
								<type>select</type>
								<items type="array">
								<numIndex index="0" type="array">
									<numIndex index="0">LLL:EXT:jk_poll/locallang_db.xml:tt_content.pi_flexform.type_horizontal</numIndex>
									<numIndex index="1">0</numIndex> 
								</numIndex>
								<numIndex index="1" type="array">
									<numIndex index="0">LLL:EXT:jk_poll/locallang_db.xml:tt_content.pi_flexform.type_vertical</numIndex>
									<numIndex index="1">1</numIndex>
								</numIndex>
								<numIndex index="2" type="array">
									<numIndex index="0">LLL:EXT:jk_poll/locallang_db.xml:tt_content.pi_flexform.type_google</numIndex>
									<numIndex index="1">2</numIndex>
								</numIndex>
								</items>
								<maxitems>1</maxitems>
								<size>1</size>
								<multiple>0</multiple>
							</config>
						</TCEforms>
					</type>
					<color>
						<TCEforms>
							<label>LLL:EXT:jk_poll/locallang_db.xml:tt_content.pi_flexform.color</label>
							<config>
								<type>input</type>
								<size>15</size>
							</config>
						</TCEforms>
					</color>
					<path_to_images>
						<TCEforms>
							<label>LLL:EXT:jk_poll/locallang_db.xml:tt_content.pi_flexform.path_to_images</label>
							<config>
								<type>input</type>
								<size>30</size>
							</config>
						</TCEforms>
					</path_to_images>
					<height_width>
						<TCEforms>
							<label>LLL:EXT:jk_poll/locallang_db.xml:tt_content.pi_flexform.height_width</label>
							<config>
								<type>input</type>
								<size>5</size>
							</config>
						</TCEforms>
					</height_width>
					<factor>
						<TCEforms>
							<label>LLL:EXT:jk_poll/locallang_db.xml:tt_content.pi_flexform.factor</label>
							<config>
								<type>input</type>
								<size>5</size>
							</config>
						</TCEforms>
					</factor>
					<show_zero_percent>
						<TCEforms>
							<label>LLL:EXT:jk_poll/locallang_db.xml:tt_content.pi_flexform.show_zero_percent</label>
							<config>
								<type>check</type>
							</config>
						</TCEforms>
					</show_zero_percent>
					<show_css_bars>
						<TCEforms>
							<label>LLL:EXT:jk_poll/locallang_db.xml:tt_content.pi_flexform.show_css_bars</label>
							<config>
								<type>check</type>
							</config>
						</TCEforms>
					</show_css_bars>
					<google_width>
						<TCEforms>
							<label>LLL:EXT:jk_poll/locallang_db.xml:tt_content.pi_flexform.google_width</label>
							<config>
								<type>input</type>
								<size>5</size>
							</config>
						</TCEforms>
					</google_width>
					<google_height>
						<TCEforms>
							<label>LLL:EXT:jk_poll/locallang_db.xml:tt_content.pi_flexform.google_height</label>
							<config>
								<type>input</type>
								<size>5</size>
							</config>
						</TCEforms>
					</google_height>
					<comments_on_result>
						<TCEforms>
							<label>LLL:EXT:jk_poll/locallang_db.xml:tt_content.pi_flexform.comments_on_result</label>
							<config>
								<type>check</type>
							</config>
						</TCEforms>
					</comments_on_result>
					<link_to_poll>
						<TCEforms>
							<label>LLL:EXT:jk_poll/locallang_db.xml:tt_content.pi_flexform.link_to_poll</label>
							<config>
								<type>check</type>
							</config>
						</TCEforms>
					</link_to_poll>
					<result_limit>
						<TCEforms>
							<label>LLL:EXT:jk_poll/locallang_db.xml:tt_content.pi_flexform.result_limit</label>
							<config>
								<type>input</type>
								<size>2</size>
							</config>
						</TCEforms>
					</result_limit>
				</el>
			</ROOT>
		</s_result>
	
		<s_list>
			<ROOT>
				<TCEforms>
					<sheetTitle>LLL:EXT:jk_poll/locallang_db.xml:tt_content.pi_flexform.sheet_list</sheetTitle>
				</TCEforms>
				<type>array</type>
				<el>	     
					<amount>
						<TCEforms>
							<label>LLL:EXT:jk_poll/locallang_db.xml:tt_content.pi_flexform.amount</label>
							<config>
								<type>input</type>
								<size>5</size>
							</config>
						</TCEforms>
					</amount>
					<show_first>
						<TCEforms>
							<label>LLL:EXT:jk_poll/locallang_db.xml:tt_content.pi_flexform.show_first</label>
							<config>
								<type>check</type>
							</config>
						</TCEforms>
					</show_first>
					<hide_current>
						<TCEforms>
							<label>LLL:EXT:jk_poll/locallang_db.xml:tt_content.pi_flexform.hide_current</label>
							<config>
								<type>check</type>
							</config>
						</TCEforms>
					</hide_current>
					<vote_old>
						<TCEforms>
							<label>LLL:EXT:jk_poll/locallang_db.xml:tt_content.pi_flexform.vote_old</label>
							<config>
								<type>check</type>
							</config>
						</TCEforms>
					</vote_old>
					<pagebrowser>
						<TCEforms>
							<label>LLL:EXT:jk_poll/locallang_db.xml:tt_content.pi_flexform.pagebrowser</label>
							<config>
								<type>check</type>
							</config>
						</TCEforms>
					</pagebrowser>
					<pagebrowser_items>
						<TCEforms>
							<label>LLL:EXT:jk_poll/locallang_db.xml:tt_content.pi_flexform.pagebrowser_items</label>
							<config>
								<type>input</type>
								<size>5</size>
							</config>
						</TCEforms>
					</pagebrowser_items>
					<show_results_in_list>
						<TCEforms>
							<label>LLL:EXT:jk_poll/locallang_db.xml:tt_content.pi_flexform.show_results_in_list</label>
							<config>
								<type>check</type>
							</config>
						</TCEforms>
					</show_results_in_list>
					<PIDitemDisplay>
						<TCEforms>
						<exclude>1</exclude>
						<label>LLL:EXT:jk_poll/locallang_db.xml:tt_content.pi_flexform.PIDitemDisplay</label>
						<config>
							<type>group</type>
							<internal_type>db</internal_type>
							<allowed>pages</allowed>
							<size>1</size>
							<maxitems>1</maxitems>
							<minitems>0</minitems>
							<show_thumbs>1</show_thumbs>
						</config>
						</TCEforms>
					</PIDitemDisplay>
					<backlink>
						<TCEforms>
							<label>LLL:EXT:jk_poll/locallang_db.xml:tt_content.pi_flexform.backlink</label>
							<config>
								<type>check</type>
							</config>
						</TCEforms>
					</backlink>
				</el>
			</ROOT>
		</s_list>
	
	</sheets>
</T3DataStructure>
